{
    "survey_type": "استبيان التقييم الأول",
    "survey_date": "2022-08-09",
    "case_id": "8",
    "child_name": "منار محمد عبد الحفيظ",
    "dob": "2015-09-04",
    "gender": "أنثى",
    "submission_timestamp": "2025-08-16T22:04:01.054824",
    "school_attendance": {
        "ar_key": "هل يذهب إلى المدرسة/الحضانة",
        "value": "نعم"
    },
    "school_year": {
        "ar_key": "العام الدراسي",
        "value": "2022"
    },
    "school_duration": {
        "ar_key": "المدة التي قضاها",
        "value": "3 سنوات"
    },
    "school_type": {
        "ar_key": "نوعها",
        "value": "حضانة - عربي"
    },
    "school_discontinue": {
        "ar_key": "سبب عدم الاستمرار",
        "value": "الخوف"
    },
    "care_center": {
        "ar_key": "هل يذهب إلى مركز/أكاديمية رعاية",
        "value": "لا"
    },
    "care_duration": {
        "ar_key": "المدة التي قضاها",
        "value": "سنة واحدة"
    },
    "care_type": {
        "ar_key": "نوعها",
        "value": "تأهيلي"
    },
    "care_discontinue": {
        "ar_key": "سبب عدم الاستمرار",
        "value": "الخوف"
    },
    "academic_issues": {
        "ar_key": "هل توجد مشاكل في التحصيل الدراسي",
        "value": "لا"
    },
    "academic_issues_type": {
        "ar_key": "نوعها",
        "value": "الخوف"
    },
    "abnormal_dev": {
        "ar_key": "هل كانت هناك إشارات تدل على نمو غير طبيعي",
        "value": "نعم"
    },
    "abnormal_dev_what": {
        "ar_key": "ما هي",
        "value": "صغر الرجلين"
    },
    "diagnosis_what": {
        "ar_key": "ما هو تشخيصه",
        "value": "حركي"
    },
    "breastfeeding_duration": {
        "ar_key": "مدة الرضاعة",
        "value": "عامان"
    },
    "breastfeeding_type": {
        "ar_key": "نوع الرضاعة",
        "value": "صناعي"
    },
    "weaning": {
        "ar_key": "الفطام",
        "value": "مفاجئ"
    },
    "weaning_age": {
        "ar_key": "سن الفطام",
        "value": "عامان"
    },
    "breastfeeding_problems": {
        "ar_key": "هل وُجدت مشاكل بالرضاعة",
        "value": "لا"
    },
    "teething": {
        "ar_key": "التسنين",
        "value": "عادي"
    },
    "crawling": {
        "ar_key": "الحبو",
        "value": "عادي"
    },
    "sitting": {
        "ar_key": "الجلوس",
        "value": "عادي"
    },
    "standing": {
        "ar_key": "الوقوف",
        "value": "لا تقف"
    },
    "walking_start": {
        "ar_key": "متى بدأ المشي",
        "value": "لم تمش"
    },
    "walking": {
        "ar_key": "المشي",
        "value": "لا تمش"
    },
    "diaper_free": {
        "ar_key": "متى تخلص من الحفاض",
        "value": "لم تتخلص"
    },
    "bathroom_request": {
        "ar_key": "استخدام الحمام الآن",
        "value": "يحتاج تدريب"
    },
    "bathroom_independence": {
        "ar_key": "يدخل الحمام",
        "value": "مساعدة كلية"
    },
    "vision_issues": {
        "ar_key": "هل يعاني من أي ضعف في درجة الإبصار",
        "value": "لا"
    },
    "vision_type": {
        "ar_key": "نوعه",
        "value": "-"
    },
    "vision_severity": {
        "ar_key": "شدته",
        "value": "-"
    },
    "hearing_issues": {
        "ar_key": "هل يعاني من ضعف سمع",
        "value": "نعم"
    },
    "hearing_type": {
        "ar_key": "نوعه",
        "value": "مركزي"
    },
    "hearing_severity": {
        "ar_key": "شدته",
        "value": "-"
    },
    "hearing_aid": {
        "ar_key": "هل يرتدي سماعات",
        "value": "لا"
    },
    "hearing_aid_type": {
        "ar_key": "نوعها",
        "value": "-"
    },
    "cochlear_implant": {
        "ar_key": "هل لديه زرع قوقعة",
        "value": "لا"
    },
    "cochlear_since": {
        "ar_key": "منذ متى",
        "value": "-"
    },
    "speech_tone": {
        "ar_key": "هل يتحدث الطفل بنبرة صوت ثابتة",
        "value": "نعم"
    },
    "speech_volume": {
        "ar_key": "هل يتحدث الطفل بصوت",
        "value": "منخفض"
    },
    "drooling": {
        "ar_key": "هل يعاني الطفل من سيلان اللعاب",
        "value": "لا"
    },
    "swallowing": {
        "ar_key": "هل يعاني الطفل من صعوبة بلع",
        "value": "لا"
    },
    "breathing": {
        "ar_key": "هل يعاني الطفل من اضطرابات في التنفس",
        "value": "لا"
    },
    "breathing_type": {
        "ar_key": "نوع اضطراب التنفس",
        "value": "شفط"
    },
    "iq_test": {
        "ar_key": "هل تم إجراء اختبار ذكاء (IQ)",
        "value": "نعم"
    },
    "iq_score": {
        "ar_key": "الدرجة",
        "value": "30"
    },
    "hearing_test": {
        "ar_key": "هل تم إجراء مقياس سمع",
        "value": "لا"
    },
    "hearing_score": {
        "ar_key": "الدرجة",
        "value": "-"
    },
    "ear_pressure": {
        "ar_key": "هل تم إجراء اختبار ضغط الأذن",
        "value": "لا"
    },
    "language_test": {
        "ar_key": "هل تم إجراء اختبار لغة",
        "value": "لا"
    },
    "speech_test": {
        "ar_key": "هل تم إجراء اختبار نطق",
        "value": "لا"
    },
    "case_acceptance": {
        "ar_key": "مدى تقبل الحالة للتأهيل",
        "value": "-"
    },
    "family_acceptance": {
        "ar_key": "مدى تقبل الأسرة للمشكلة",
        "value": "جيد"
    },
    "speech_therapy": {
        "ar_key": "هل يتلقى جلسات تخاطب",
        "value": "نعم"
    },
    "speech_therapy_progress": {
        "ar_key": "مدى التقدم",
        "value": "جيد"
    },
    "physical_therapy": {
        "ar_key": "هل يتلقى علاج طبيعي",
        "value": "لا"
    },
    "physical_therapy_progress": {
        "ar_key": "مدى التقدم",
        "value": "-"
    },
    "computer_therapy": {
        "ar_key": "هل يتعامل مع الكمبيوتر",
        "value": "لا"
    },
    "computer_therapy_progress": {
        "ar_key": "مدى التقدم",
        "value": "-"
    },
    "skills_therapy": {
        "ar_key": "هل يتلقى تنمية مهارات",
        "value": "لا"
    },
    "skills_therapy_progress": {
        "ar_key": "مدى التقدم",
        "value": "-"
    },
    "favorite_food": {
        "ar_key": "ما أكثر المأكولات أو المشروبات التي يفضلها",
        "value": "الحلوى"
    },
    "favorite_games": {
        "ar_key": "ما أكثر الألعاب التي يحبها",
        "value": "-"
    },
    "other_likes": {
        "ar_key": "أشياء أخرى يحبها",
        "value": "-"
    },
    "dislikes": {
        "ar_key": "أشياء ينزعج منها",
        "value": "-"
    },
    "living_with": {
        "ar_key": "مع من يعيش الطفل",
        "value": "أسرته"
    },
    "attached_people": {
        "ar_key": "هل يوجد أشخاص مرتبط بهم (من الأسرة أو المحيط) ويؤثرون فيه",
        "value": "لا"
    },
    "caregiver": {
        "ar_key": "من هو القائم برعاية الطفل",
        "value": "أمه"
    },
    "economic_status": {
        "ar_key": "الوضع الاقتصادي",
        "value": "جيد"
    },
    "cultural_status": {
        "ar_key": "الوضع الثقافي",
        "value": "جيد"
    },
    "social_status": {
        "ar_key": "الوضع الاجتماعي",
        "value": "جيد"
    },
    "family_relationship": {
        "ar_key": "طبيعة العلاقة الأسرية",
        "value": "جيدة"
    },
    "family_acceptance_rehab": {
        "ar_key": "مدى تقبل الأسرة للاضطراب واستعدادها للمشاركة في التأهيل",
        "value": "حماسي"
    },
    "mother_health_pregnancy": {
        "ar_key": "صحة الأم أثناء الحمل كانت",
        "value": "غير مستقرة"
    },
    "birth_type": {
        "ar_key": "نوع الولادة",
        "value": "طبيعية"
    },
    "birth_weight": {
        "ar_key": "وزن الطفل عند الولادة",
        "value": "1 كجم"
    },
    "birth_cry": {
        "ar_key": "هل صرخ الطفل صرخة الميلاد",
        "value": "لا"
    },
    "head_size": {
        "ar_key": "حجم رأس الطفل عند الولادة",
        "value": "طبيعي"
    },
    "head_size_value": {
        "ar_key": "كان",
        "value": "صغير"
    },
    "birth_defects": {
        "ar_key": "هل كانت هناك عيوب خلقية بعد الولادة",
        "value": "لا"
    },
    "birth_defects_what": {
        "ar_key": "ما هي",
        "value": "-"
    }
}